app/__init__.py
app/_version.py
app/main.py
app/report_components/__init__.py
app/report_components/data_processor.py
app/report_components/interpolation.py
app/report_components/report_generator.py
app/report_components/template/report_template.html.j2
app/scripts/test_datetime.xml
app/scripts/test_entities.xml
app/scripts/test_entity_file.xml
app/scripts/data/data.ent.csv
app/utils/__init__.py
app/utils/performance_utils.py
datamimic_perf-0.1.0.post1.dev0.dist-info/LICENSE
datamimic_perf-0.1.0.post1.dev0.dist-info/METADATA
datamimic_perf-0.1.0.post1.dev0.dist-info/WHEEL
datamimic_perf-0.1.0.post1.dev0.dist-info/entry_points.txt
datamimic_perf-0.1.0.post1.dev0.dist-info/top_level.txt
datamimic_perf-0.1.0.post1.dev0.dist-info/RECORD
