Metadata-Version: 2.2
Name: datamimic-perf
Version: 0.1.0.post1.dev0
Summary: Performance tests and data mimic operations for our project
Author-email: "Rapiddweller Asia Co., Ltd." <info@rapiddweller.com>
Requires-Python: >=3.11
License-File: LICENSE
Requires-Dist: typer-cli>=0.15.1
Requires-Dist: psutil>=5.9.0
Requires-Dist: loguru>=0.6.0
Requires-Dist: jinja2>=3.1.5
Requires-Dist: matplotlib>=3.10.0
Requires-Dist: pip>=25.0.1
Requires-Dist: setuptools>=75.8.0
Requires-Dist: wheel>=0.42.0
